sql_lsp/__init__.py
sql_lsp/cli.py
sql_lsp/completion.py
sql_lsp/config.py
sql_lsp/database.py
sql_lsp/mysql_connector.py
sql_lsp/server.py
sql_lsp/utils.py
sql_lsp-0.0.7.dist-info/METADATA
sql_lsp-0.0.7.dist-info/WHEEL
sql_lsp-0.0.7.dist-info/entry_points.txt
sql_lsp-0.0.7.dist-info/RECORD
